lstail/__init__.py
lstail/cli.py
lstail/config.py
lstail/constants.py
lstail/error.py
lstail/http.py
lstail/logger.py
lstail/options.py
lstail/prompt.py
lstail/reader.py
lstail/dto/__init__.py
lstail/dto/column.py
lstail/dto/configuration.py
lstail/dto/display.py
lstail/dto/format.py
lstail/dto/kibana.py
lstail/dto/kibana_saved_search.py
lstail/dto/parser.py
lstail/dto/query.py
lstail/dto/server.py
lstail/query/__init__.py
lstail/query/base.py
lstail/query/elasticsearch_2.py
lstail/query/elasticsearch_6.py
lstail/query/elasticsearch_7.py
lstail/query/factory.py
lstail/query/kibana_saved_search.py
lstail/util/__init__.py
lstail/util/color.py
lstail/util/debug.py
lstail/util/formatter.py
lstail/util/http.py
lstail/util/safe_munch.py
lstail/util/timestamp.py
lstail-1.2.0.dist-info/LICENSE
lstail-1.2.0.dist-info/METADATA
lstail-1.2.0.dist-info/WHEEL
lstail-1.2.0.dist-info/entry_points.txt
lstail-1.2.0.dist-info/top_level.txt
lstail-1.2.0.dist-info/RECORD
