Metadata-Version: 2.1
Name: lstail
Version: 1.2.0
Summary: Logstash command line query tool, a bit like tail for Logstash/ElasticSearch
Home-page: https://github.com/eht16/lstail/
Author: Enrico Tröger
Author-email: enrico.troeger@uvena.de
License: MIT
Project-URL: Source code, https://github.com/eht16/lstail/
Project-URL: Documentation, https://lstail.org/
Keywords: logging logs logstash query tail log-viewer cli
Classifier: Environment :: Console
Classifier: Development Status :: 5 - Production/Stable
Classifier: Intended Audience :: Developers
Classifier: Intended Audience :: System Administrators
Classifier: License :: OSI Approved :: MIT License
Classifier: Operating System :: OS Independent
Classifier: Programming Language :: Python
Classifier: Programming Language :: Python :: 3
Classifier: Topic :: Internet :: Log Analysis
Classifier: Topic :: System :: Logging
Requires-Python: >=3.9
License-File: LICENSE
Requires-Dist: prompt-toolkit
